{
    "editor.fontFamily": "JetBrainsMono Nerd Font",
    "editor.fontSize": 14,
    "editor.lineHeight": 32,
    "workbench.productIconTheme": "fluent-icons",
    "workbench.iconTheme": "material-icon-theme",
    "editor.minimap.enabled": false,
    "editor.cursorBlinking": "solid",
    "editor.smoothScrolling": true,
    
    "eslint.validate": [
        "typescript",
        "typescriptreact",
        "javascript",
        "javascriptreact"
    ],
    "[jsonc]": {
        "editor.defaultFormatter": "vscode.json-language-features"
    },
    "[typescript]": {
        "editor.codeActionsOnSave": {
            "source.fixAll.eslint": true
        }
    },
    "[javascript]": {
        "editor.codeActionsOnSave": {
            "source.fixAll.eslint": true
        }
    },
    "[javascriptreact]": {
        "editor.codeActionsOnSave": {
            "source.fixAll.eslint": true
        }
    },
    "[typescriptreact]": {
        "editor.codeActionsOnSave": {
            "source.fixAll.eslint": true
        }
    },
    // Workbench
    "workbench.startupEditor": "none",
    "workbench.colorTheme": "Nord",
    "workbench.activityBar.visible": false,

    // Git
    "git.autofetch": true,
    
    // Neovim configs
    "vscode-neovim.neovimExecutablePaths.linux": "/usr/bin/nvim",
    "vscode-neovim.neovimInitVimPaths.linux": "$HOME/.config/nvim/init.lua",
}